pytensordock/__init__.py
pytensordock/api.py
pytensordock-0.1.1.dist-info/LICENSE
pytensordock-0.1.1.dist-info/METADATA
pytensordock-0.1.1.dist-info/WHEEL
pytensordock-0.1.1.dist-info/top_level.txt
pytensordock-0.1.1.dist-info/RECORD
