Metadata-Version: 2.1
Name: pytensordock
Version: 0.1.1
Summary: A Python wrapper for TensorDock API
Author-email: Nishant Gajjar <nishantkgajjar@outlook.com>
Project-URL: Homepage, https://github.com/nishantg96/pytensordock
Project-URL: Issues, https://github.com/nishantg96/pytensordock/issues
Classifier: Programming Language :: Python :: 3
Classifier: License :: OSI Approved :: MIT License
Classifier: Operating System :: OS Independent
Classifier: Development Status :: 6 - Mature
Requires-Python: >=3.7
License-File: LICENSE
Requires-Dist: requests
